oqtimal/__init__.py
oqtimal/optimal_transport.py
oqtimal/utils.py
oqtimal/algorithms/__init__.py
oqtimal/algorithms/hungarian.py
oqtimal/algorithms/simplex.py
oqtimal/algorithms/sinkhorn_knopp.py
oqtimal-0.0.4.dist-info/LICENSE
oqtimal-0.0.4.dist-info/METADATA
oqtimal-0.0.4.dist-info/WHEEL
oqtimal-0.0.4.dist-info/top_level.txt
oqtimal-0.0.4.dist-info/RECORD
